setup.py
liwakura_distributions/Binomialdistribution.py
liwakura_distributions/Gaussiandistribution.py
liwakura_distributions/Generaldistribution.py
liwakura_distributions/__init__.py
liwakura_distributions.egg-info/PKG-INFO
liwakura_distributions.egg-info/SOURCES.txt
liwakura_distributions.egg-info/dependency_links.txt
liwakura_distributions.egg-info/not-zip-safe
liwakura_distributions.egg-info/top_level.txt