Metadata-Version: 2.1
Name: liwakura-distributions
Version: 0.0.1
Summary: Gaussian distributions
Home-page: UNKNOWN
Author: Lain Iwakura
Author-email: dad0bc1a.4c35.4a3f.851c.bae30d+pypi@gmail.com
License: UNKNOWN
Platform: UNKNOWN
